jaradtransformers/__init__.py
jaradtransformers/_transformers.py
jaradtransformers-0.1.4.dist-info/DESCRIPTION.rst
jaradtransformers-0.1.4.dist-info/METADATA
jaradtransformers-0.1.4.dist-info/RECORD
jaradtransformers-0.1.4.dist-info/WHEEL
jaradtransformers-0.1.4.dist-info/metadata.json
jaradtransformers-0.1.4.dist-info/top_level.txt
