Metadata-Version: 2.0
Name: jaradtransformers
Version: 0.1.4
Summary: Custom transformers for SKLearn pipelines
Home-page: UNKNOWN
Author: Jarad Collier
Author-email: jnscollier@gmail.com
License: MIT
Platform: UNKNOWN
Requires-Dist: scikit-learn
Requires-Dist: scipy
